htql.cp313-win_amd64.pyd
htql-1.0.0.dist-info/licenses/LICENSE
htql-1.0.0.dist-info/METADATA
htql-1.0.0.dist-info/WHEEL
htql-1.0.0.dist-info/top_level.txt
htql-1.0.0.dist-info/RECORD
